generative_content_pipeline_scraping/__init__.py
generative_content_pipeline_scraping/data.py
generative_content_pipeline_scraping/settings.py
generative_content_pipeline_scraping/tables.py
generative_content_pipeline_scraping-0.1.6.dist-info/METADATA
generative_content_pipeline_scraping-0.1.6.dist-info/WHEEL
generative_content_pipeline_scraping-0.1.6.dist-info/top_level.txt
generative_content_pipeline_scraping-0.1.6.dist-info/RECORD
