Metadata-Version: 2.4
Name: generative-content-pipeline-scraping
Version: 0.1.6
Summary: Module which provides scraping logic and stores data in the chosen infrastructure
Requires-Dist: boto3
Requires-Dist: sqlalchemy
Requires-Dist: pydantic
Requires-Dist: pydantic-settings
Requires-Dist: asyncpg
Requires-Dist: psycopg2
Requires-Dist: aiosqlite
Requires-Dist: bs4
Requires-Dist: cssutils
Requires-Dist: Pillow
Requires-Dist: gutenbergpy
Requires-Dist: requests
Provides-Extra: dev
Requires-Dist: ipykernel; extra == "dev"
